{
  "DataEntityMetadataJson": {
    "TablaEquivalenciasCpp": "{\"name\":\"TablaEquivalenciasCpp\",\"title\":\"TablaEquivalenciasCpp\",\"x-ms-permission\":\"read-write\",\"schema\":{\"type\":\"array\",\"items\":{\"type\":\"object\",\"properties\":{\"No\":{\"type\":\"string\",\"x-ms-keyOrder\":0,\"x-ms-keyType\":\"none\",\"x-ms-sort\":\"none\",\"title\":\"No\"},\"Marca\":{\"type\":\"string\",\"x-ms-keyOrder\":0,\"x-ms-keyType\":\"none\",\"x-ms-sort\":\"none\",\"title\":\"Marca\"},\"RefSAP\":{\"type\":\"string\",\"x-ms-keyOrder\":0,\"x-ms-keyType\":\"none\",\"x-ms-sort\":\"none\",\"title\":\"RefSAP\"},\"RefFabricante\":{\"type\":\"string\",\"x-ms-keyOrder\":0,\"x-ms-keyType\":\"none\",\"x-ms-sort\":\"none\",\"title\":\"RefFabricante\"},\"Equivalencia\":{\"type\":\"string\",\"x-ms-keyOrder\":0,\"x-ms-keyType\":\"none\",\"x-ms-sort\":\"none\",\"title\":\"Equivalencia\"},\"__PowerAppsId__\":{\"type\":\"string\",\"x-ms-keyOrder\":1,\"x-ms-keyType\":\"primary\",\"x-ms-sort\":\"none\",\"x-ms-permission\":\"read-only\",\"title\":\"Row id\"}}}}}"
  },
  "EntityName": "TablaEquivalenciasCpp",
  "TableName": "TablaEquivalenciasCpp"
}